{"type":"object","description":"UI Definition for the created page","additionalProperties":false,"properties":{"IsHideCardOwnerName":{"type":"boolean","description":"Hide card Owner name","default":false,"nullable":true},"CardOwnerNameValue":{"type":"string","description":"Fill the value of CardOwnerName input box","default":"","maxLength":50,"nullable":true},"CardOwnerIdValue":{"type":"string","description":"Card onwer Id aka teudat zeut","default":"","nullable":true},"IsHideCardOwnerPhone":{"type":"boolean","description":"Hide card owner phone number","default":false,"nullable":true},"CardOwnerPhoneValue":{"type":"string","description":"Fill the value of CardOwnerPhone input box","maxLength":50,"nullable":true},"IsCardOwnerPhoneRequired":{"type":"boolean","description":"Is CardOwnerPhone input box required","default":true,"nullable":true},"CardOwnerEmailValue":{"type":"string","description":"fill the value of card owner email","maxLength":50,"nullable":true},"IsHideCardOwnerEmail":{"type":"boolean","description":"Hide card owner email","default":false,"nullable":true},"IsCardOwnerEmailRequired":{"type":"boolean","description":"Is card owner email input box required","default":true,"nullable":true},"IsHideCardOwnerIdentityNumber":{"type":"boolean","description":"Hide card ownder identity number","default":false,"nullable":true},"IsHideCVV":{"type":"boolean","description":"Hide card number CVV","default":false,"nullable":true},"CSSUrl":{"type":"string","description":"Full URL address of CSS file. it will be injected to page, required CardCom premition (http(s)://site.com/file.css)","maxLength":250,"nullable":true},"CustomFields":{"type":"array","description":"Fill the value of CustomFields input box by Field Id","nullable":true,"items":{"type":"object","description":"Custom field","additionalProperties":false,"properties":{"Id":{"type":"integer","description":"Custom field id","maximum":25,"minimum":1},"Value":{"type":"string","description":"Custom field value","maxLength":50}},"x-readme-ref-name":"CustomField"}},"GooglePayBtnDesign":{"description":"Set how the Google Pay button will appear","nullable":true,"oneOf":[{"type":"object","additionalProperties":false,"properties":{"ButtonColor":{"description":"GPay button color","oneOf":[{"type":"string","description":"","x-enumNames":["Default","White","Black"],"enum":["Default","White","Black"],"x-readme-ref-name":"ButtonColor"}]},"ButtonType":{"description":"GPay button type (text on the button)","default":"Buy","oneOf":[{"type":"string","description":"","x-enumNames":["Book","Buy","Checkout","Donate","Order","Pay","Plain","Subscribe"],"enum":["Book","Buy","Checkout","Donate","Order","Pay","Plain","Subscribe"],"x-readme-ref-name":"ButtonType"}]},"ButtonLocale":{"description":"GPay button language","default":"English","oneOf":[{"type":"string","description":"","x-enumNames":["Arabic","Bulgarian","Catalan","Chinese","Croatian","Czech","Danish","Dutch","English","Estonian","Finnish","French","German","Greek","Indonesian","Italian","Japanese","Korean","Malay","Norwegian","Polish","Portuguese","Russian","Serbian","Slovak","Slovenian","Spanish","Swedish","Thai","Turkish","Ukrainian"],"enum":["Arabic","Bulgarian","Catalan","Chinese","Croatian","Czech","Danish","Dutch","English","Estonian","Finnish","French","German","Greek","Indonesian","Italian","Japanese","Korean","Malay","Norwegian","Polish","Portuguese","Russian","Serbian","Slovak","Slovenian","Spanish","Swedish","Thai","Turkish","Ukrainian"],"x-readme-ref-name":"ButtonLocale"}]},"ButtonWidth":{"type":"string","description":"GPay button width. Default 328 (px)","default":"328","nullable":true},"ButtonHeight":{"type":"string","description":"GPay button height. Default 40 (px)","default":"4","nullable":true}},"x-readme-ref-name":"GooglePayBtnDesign"}]}},"x-readme-ref-name":"UIDefinition"}